{
  "id": 189205663,
  "node_id": "MDEwOlJlcG9zaXRvcnkxODkyMDU2NjM=",
  "name": "TinyWebServer",
  "full_name": "qinguoyi/TinyWebServer",
  "private": false,
  "owner": {
    "login": "qinguoyi",
    "id": 25760295,
    "node_id": "MDQ6VXNlcjI1NzYwMjk1",
    "avatar_url": "https://avatars.githubusercontent.com/u/25760295?v=4",
    "gravatar_id": "",
    "url": "https://api.github.com/users/qinguoyi",
    "html_url": "https://github.com/qinguoyi",
    "followers_url": "https://api.github.com/users/qinguoyi/followers",
    "following_url": "https://api.github.com/users/qinguoyi/following{/other_user}",
    "gists_url": "https://api.github.com/users/qinguoyi/gists{/gist_id}",
    "starred_url": "https://api.github.com/users/qinguoyi/starred{/owner}{/repo}",
    "subscriptions_url": "https://api.github.com/users/qinguoyi/subscriptions",
    "organizations_url": "https://api.github.com/users/qinguoyi/orgs",
    "repos_url": "https://api.github.com/users/qinguoyi/repos",
    "events_url": "https://api.github.com/users/qinguoyi/events{/privacy}",
    "received_events_url": "https://api.github.com/users/qinguoyi/received_events",
    "type": "User",
    "user_view_type": "public",
    "site_admin": false
  },
  "html_url": "https://github.com/qinguoyi/TinyWebServer",
  "description": ":fire: Linux\u4e0bC++\u8f7b\u91cf\u7ea7WebServer\u670d\u52a1\u5668",
  "fork": false,
  "url": "https://api.github.com/repos/qinguoyi/TinyWebServer",
  "forks_url": "https://api.github.com/repos/qinguoyi/TinyWebServer/forks",
  "keys_url": "https://api.github.com/repos/qinguoyi/TinyWebServer/keys{/key_id}",
  "collaborators_url": "https://api.github.com/repos/qinguoyi/TinyWebServer/collaborators{/collaborator}",
  "teams_url": "https://api.github.com/repos/qinguoyi/TinyWebServer/teams",
  "hooks_url": "https://api.github.com/repos/qinguoyi/TinyWebServer/hooks",
  "issue_events_url": "https://api.github.com/repos/qinguoyi/TinyWebServer/issues/events{/number}",
  "events_url": "https://api.github.com/repos/qinguoyi/TinyWebServer/events",
  "assignees_url": "https://api.github.com/repos/qinguoyi/TinyWebServer/assignees{/user}",
  "branches_url": "https://api.github.com/repos/qinguoyi/TinyWebServer/branches{/branch}",
  "tags_url": "https://api.github.com/repos/qinguoyi/TinyWebServer/tags",
  "blobs_url": "https://api.github.com/repos/qinguoyi/TinyWebServer/git/blobs{/sha}",
  "git_tags_url": "https://api.github.com/repos/qinguoyi/TinyWebServer/git/tags{/sha}",
  "git_refs_url": "https://api.github.com/repos/qinguoyi/TinyWebServer/git/refs{/sha}",
  "trees_url": "https://api.github.com/repos/qinguoyi/TinyWebServer/git/trees{/sha}",
  "statuses_url": "https://api.github.com/repos/qinguoyi/TinyWebServer/statuses/{sha}",
  "languages_url": "https://api.github.com/repos/qinguoyi/TinyWebServer/languages",
  "stargazers_url": "https://api.github.com/repos/qinguoyi/TinyWebServer/stargazers",
  "contributors_url": "https://api.github.com/repos/qinguoyi/TinyWebServer/contributors",
  "subscribers_url": "https://api.github.com/repos/qinguoyi/TinyWebServer/subscribers",
  "subscription_url": "https://api.github.com/repos/qinguoyi/TinyWebServer/subscription",
  "commits_url": "https://api.github.com/repos/qinguoyi/TinyWebServer/commits{/sha}",
  "git_commits_url": "https://api.github.com/repos/qinguoyi/TinyWebServer/git/commits{/sha}",
  "comments_url": "https://api.github.com/repos/qinguoyi/TinyWebServer/comments{/number}",
  "issue_comment_url": "https://api.github.com/repos/qinguoyi/TinyWebServer/issues/comments{/number}",
  "contents_url": "https://api.github.com/repos/qinguoyi/TinyWebServer/contents/{+path}",
  "compare_url": "https://api.github.com/repos/qinguoyi/TinyWebServer/compare/{base}...{head}",
  "merges_url": "https://api.github.com/repos/qinguoyi/TinyWebServer/merges",
  "archive_url": "https://api.github.com/repos/qinguoyi/TinyWebServer/{archive_format}{/ref}",
  "downloads_url": "https://api.github.com/repos/qinguoyi/TinyWebServer/downloads",
  "issues_url": "https://api.github.com/repos/qinguoyi/TinyWebServer/issues{/number}",
  "pulls_url": "https://api.github.com/repos/qinguoyi/TinyWebServer/pulls{/number}",
  "milestones_url": "https://api.github.com/repos/qinguoyi/TinyWebServer/milestones{/number}",
  "notifications_url": "https://api.github.com/repos/qinguoyi/TinyWebServer/notifications{?since,all,participating}",
  "labels_url": "https://api.github.com/repos/qinguoyi/TinyWebServer/labels{/name}",
  "releases_url": "https://api.github.com/repos/qinguoyi/TinyWebServer/releases{/id}",
  "deployments_url": "https://api.github.com/repos/qinguoyi/TinyWebServer/deployments",
  "created_at": "2019-05-29T10:41:34Z",
  "updated_at": "2024-12-27T15:40:56Z",
  "pushed_at": "2024-07-05T13:35:04Z",
  "git_url": "git://github.com/qinguoyi/TinyWebServer.git",
  "ssh_url": "git@github.com:qinguoyi/TinyWebServer.git",
  "clone_url": "https://github.com/qinguoyi/TinyWebServer.git",
  "svn_url": "https://github.com/qinguoyi/TinyWebServer",
  "homepage": "",
  "size": 57302,
  "stargazers_count": 17155,
  "watchers_count": 17155,
  "language": "C++",
  "has_issues": true,
  "has_projects": true,
  "has_downloads": true,
  "has_wiki": true,
  "has_pages": false,
  "has_discussions": false,
  "forks_count": 4002,
  "mirror_url": null,
  "archived": false,
  "disabled": false,
  "open_issues_count": 106,
  "license": {
    "key": "apache-2.0",
    "name": "Apache License 2.0",
    "spdx_id": "Apache-2.0",
    "url": "https://api.github.com/licenses/apache-2.0",
    "node_id": "MDc6TGljZW5zZTI="
  },
  "allow_forking": true,
  "is_template": false,
  "web_commit_signoff_required": false,
  "topics": [
    "cpp",
    "http-server",
    "tinywebserver",
    "webbench",
    "webserver"
  ],
  "visibility": "public",
  "forks": 4002,
  "open_issues": 106,
  "watchers": 17155,
  "default_branch": "master",
  "permissions": {
    "admin": false,
    "maintain": false,
    "push": false,
    "triage": false,
    "pull": true
  },
  "temp_clone_token": "",
  "network_count": 4002,
  "subscribers_count": 89,
  "languages": {
    "C++": 65298,
    "C": 12469,
    "HTML": 5498,
    "Makefile": 2643,
    "Roff": 2411,
    "Shell": 24
  },
  "default_branch_commit_sha": "4bcf88762f85135e9bd46a1032e815e458de6f2e"
}